pyquack/__init__.py
pyquack/__main__.py
pyquack/_async.py
pyquack/models.py
pyquack/sync.py
pyquack-0.2.1.dist-info/LICENSE
pyquack-0.2.1.dist-info/WHEEL
pyquack-0.2.1.dist-info/METADATA
pyquack-0.2.1.dist-info/RECORD
